akkoma/Akkoma.py
akkoma/__init__.py
Akkoma.py-0.1.6.dist-info/LICENSE
Akkoma.py-0.1.6.dist-info/METADATA
Akkoma.py-0.1.6.dist-info/WHEEL
Akkoma.py-0.1.6.dist-info/top_level.txt
Akkoma.py-0.1.6.dist-info/RECORD
