Metadata-Version: 2.1
Name: Akkoma.py
Version: 0.1.6
Summary: Python wrapper for the [Akkoma](https://akkoma.dev/AkkomaGang/akkoma) API.
Home-page: https://git.mastodont.cat/spla/Akkoma.py
Author: spla
Author-email: llemena_obrer.0u@icloud.com
Project-URL: Bug Tracker, https://git.mastodont.cat/spla/Akkoma.py/issues
Keywords: akkoma api microblogging
Classifier: License :: OSI Approved :: GNU General Public License v3 (GPLv3)
Classifier: Topic :: Software Development :: Libraries :: Python Modules
Classifier: Topic :: Communications
Classifier: Intended Audience :: Developers
Classifier: Programming Language :: Python :: 3
Requires-Python: >=3.8
License-File: LICENSE
Requires-Dist: pytz
Requires-Dist: requests
Requires-Dist: python-dateutil
Requires-Dist: decorator
